{"State.7c42b0d4-fae0-42be-99b7-7afd20231a11": {"created_at": "2020-04-01T23:43:44.222459", "updated_at": "2020-04-01T23:43:44.222512", "name": "Arizona", "id": "7c42b0d4-fae0-42be-99b7-7afd20231a11", "__class__": "State"}, "State.b6b1911a-21ac-4715-8189-fde96bc10aed": {"created_at": "2020-04-01T23:43:44.219505", "updated_at": "2020-04-01T23:43:44.219556", "name": "California", "id": "b6b1911a-21ac-4715-8189-fde96bc10aed", "__class__": "State"}, "Place.750227f8-6b98-4b11-a355-140f36b4c7ef": {"number_bathrooms": 2, "user_id": "0001", "number_rooms": 4, "price_by_night": 300, "city_id": "0001", "created_at": "2020-04-01T23:43:44.226850", "longitude": -122.431297, "updated_at": "2020-04-01T23:43:44.226909", "name": "My little house", "id": "750227f8-6b98-4b11-a355-140f36b4c7ef", "__class__": "Place", "max_guest": 10, "latitude": 37.773972}, "Place.72ba3f17-6754-4b2d-93fe-bd9b6fd84c7f": {"name": "salmen", "updated_at": "2020-04-01T23:45:49.664558", "created_at": "2020-04-01T23:45:49.664503", "id": "0010", "__class__": "Place"}}